redner.so
Imath.py
libredner_tf_data_ptr_no_cxx11_abi.so
libtbb.so.2
OpenEXR.cpython-36m-x86_64-linux-gnu.so
libredner_tf_data_ptr_cxx11_abi.so
libembree3.so.3
libtbbmalloc.so.2
pyredner/load_obj.py
pyredner/render_utils.py
pyredner/camera.py
pyredner/image.py
pyredner/render_pytorch.py
pyredner/__init__.py
pyredner/channels.py
pyredner/area_light.py
pyredner/scene.py
pyredner/material.py
pyredner/load_mitsuba.py
pyredner/envmap.py
pyredner/geometry_images.py
pyredner/transform.py
pyredner/camera_type.py
pyredner/device.py
pyredner/sampler_type.py
pyredner/utils.py
pyredner/texture.py
pyredner/object.py
pyredner/shape.py
pyredner/save_obj.py
redner_test-0.0.1.dist-info/RECORD
redner_test-0.0.1.dist-info/METADATA
redner_test-0.0.1.dist-info/WHEEL
redner_test-0.0.1.dist-info/top_level.txt
pyredner_tensorflow/load_obj.py
pyredner_tensorflow/render_utils.py
pyredner_tensorflow/camera.py
pyredner_tensorflow/image.py
pyredner_tensorflow/__init__.py
pyredner_tensorflow/channels.py
pyredner_tensorflow/render_tensorflow.py
pyredner_tensorflow/area_light.py
pyredner_tensorflow/scene.py
pyredner_tensorflow/material.py
pyredner_tensorflow/load_mitsuba.py
pyredner_tensorflow/envmap.py
pyredner_tensorflow/geometry_images.py
pyredner_tensorflow/transform.py
pyredner_tensorflow/camera_type.py
pyredner_tensorflow/device.py
pyredner_tensorflow/sampler_type.py
pyredner_tensorflow/utils.py
pyredner_tensorflow/texture.py
pyredner_tensorflow/object.py
pyredner_tensorflow/shape.py
pyredner_tensorflow/redner_enum_wrapper.py
pyredner_tensorflow/save_obj.py
